ugokukun/__init__.py
ugokukun/cannon_wrapper.py
ugokukun/keigan_wrapper.py
ugokukun/ugoku_helpers.py
ugokukun/ugoku_kun.py
Ugoku_kun-0.1.2.dist-info/LICENSE
Ugoku_kun-0.1.2.dist-info/METADATA
Ugoku_kun-0.1.2.dist-info/WHEEL
Ugoku_kun-0.1.2.dist-info/top_level.txt
Ugoku_kun-0.1.2.dist-info/RECORD
