Metadata-Version: 2.1
Name: Ugoku-kun
Version: 0.1.2
Summary: A package to control cannon camera and keigan motor for structure from motion
Author: qwasium
License: Apache License
Project-URL: Repository, https://github.com/qwasium/ugoku-kun/tree/main
Project-URL: Documenntation, https://ugoku-kun.readthedocs.io/en/latest/
Classifier: Development Status :: 4 - Beta
Classifier: Intended Audience :: Science/Research
Classifier: License :: OSI Approved :: Apache Software License
Classifier: Programming Language :: Python :: 3
Requires-Python: >=3.9
License-File: LICENSE
Requires-Dist: pyserial
Requires-Dist: requests
Requires-Dist: pandas
Requires-Dist: pykeigan-motor
Requires-Dist: timeout-decorator
